Metadata-Version: 2.1
Name: xron
Version: 1.0.2
Summary: A deep neural network basecaller for nanopore sequencing.
Home-page: https://github.com/haotianteng/Xron
Download-URL: https://github.com/haotianteng/Xron/archive/1.0.0.tar.gz
Author: Haotian Teng
Author-email: havens.teng@gmail.com
License: GPL 3.0
Keywords: basecaller,nanopore,sequencing,neural network,RNA methylation
Classifier: License :: OSI Approved :: GNU General Public License v3 (GPLv3)
License-File: LICENSE
Requires-Dist: h5py (>=2.7.0)
Requires-Dist: mappy (>=2.10.0)
Requires-Dist: numpy (>=1.13.3)
Requires-Dist: statsmodels (>=0.8.0)
Requires-Dist: tqdm (>=4.23.0)
Requires-Dist: scipy (>=1.0.1)
Requires-Dist: biopython (==1.73)
Requires-Dist: google-auth (==2.18.1)
Requires-Dist: oauthlib (==3.2.2)
Requires-Dist: packaging (>=18.0)
Requires-Dist: ont-fast5-api (>=0.3.1)
Requires-Dist: wget (>=3.2)
Requires-Dist: pysam (>=0.21.0)
Requires-Dist: tensorboard
Requires-Dist: matplotlib
Requires-Dist: seaborn
Requires-Dist: pandas
Requires-Dist: toml
Requires-Dist: fast-ctc-decode
Requires-Dist: editdistance (>=0.5.3)
Requires-Dist: torch (>=1.12.0)
Requires-Dist: torchvision (>=0.13.0)
Requires-Dist: torchaudio (>=0.12.0)
